nzpyida/__init__.py
nzpyida/aggregation.py
nzpyida/base.py
nzpyida/exceptions.py
nzpyida/filtering.py
nzpyida/frame.py
nzpyida/geo_frame.py
nzpyida/geo_series.py
nzpyida/groupby.py
nzpyida/indexing.py
nzpyida/internals.py
nzpyida/join_tables.py
nzpyida/series.py
nzpyida/sql.py
nzpyida/statistics.py
nzpyida/utils.py
nzpyida/ae/__init__.py
nzpyida/ae/apply.py
nzpyida/ae/groupedapply.py
nzpyida/ae/install.py
nzpyida/ae/result_builder.py
nzpyida/ae/shaper.py
nzpyida/ae/tapply.py
nzpyida/ae/tapply_class.py
nzpyida/analytics/__init__.py
nzpyida/analytics/auto_delete_context.py
nzpyida/analytics/model_manager.py
nzpyida/analytics/utils.py
nzpyida/analytics/exploration/__init__.py
nzpyida/analytics/exploration/distribution.py
nzpyida/analytics/exploration/relation_identification.py
nzpyida/analytics/predictive/__init__.py
nzpyida/analytics/predictive/association_rules.py
nzpyida/analytics/predictive/bayesian_networks.py
nzpyida/analytics/predictive/bisecting_kmeans.py
nzpyida/analytics/predictive/classification.py
nzpyida/analytics/predictive/decision_trees.py
nzpyida/analytics/predictive/glm.py
nzpyida/analytics/predictive/kmeans.py
nzpyida/analytics/predictive/knn.py
nzpyida/analytics/predictive/linear_regression.py
nzpyida/analytics/predictive/naive_bayes.py
nzpyida/analytics/predictive/predictive_modeling.py
nzpyida/analytics/predictive/regression.py
nzpyida/analytics/predictive/regression_trees.py
nzpyida/analytics/predictive/timeseries.py
nzpyida/analytics/predictive/two_step_clustering.py
nzpyida/analytics/transform/__init__.py
nzpyida/analytics/transform/discretization.py
nzpyida/analytics/transform/preparation.py
nzpyida/feature_selection/__init__.py
nzpyida/feature_selection/chisquared.py
nzpyida/feature_selection/entropy.py
nzpyida/feature_selection/gain_ratio.py
nzpyida/feature_selection/gini.py
nzpyida/feature_selection/info_gain.py
nzpyida/feature_selection/private.py
nzpyida/feature_selection/symmetric_uncertainty.py
nzpyida/feature_selection/tstats.py
nzpyida-1.2.dist-info/LICENSE.txt
nzpyida-1.2.dist-info/METADATA
nzpyida-1.2.dist-info/WHEEL
nzpyida-1.2.dist-info/top_level.txt
nzpyida-1.2.dist-info/RECORD
