Metadata-Version: 2.1
Name: nzpyida
Version: 1.2
Summary: Supports Custom ML/Analytics Execution Inside Netezza
Home-page: https://github.com/ibm/nzpyida
Author: IBM Corp.
Author-email: mlabenski@ibm.com,pawel.mroz1@ibm.com
License: BSD
Project-URL: Documentation, https://nzpyida.readthedocs.io/en/latest/
Project-URL: Source, https://github.com/IBM/nzpyida
Project-URL: Tracker, https://github.com/IBM/nzpyida/issues
Keywords: data analytics database development ibm netezza pandas scikitlearn scalability machine-learning knowledge discovery
Classifier: Development Status :: 4 - Beta
Classifier: Intended Audience :: Developers
Classifier: Intended Audience :: Education
Classifier: Intended Audience :: End Users/Desktop
Classifier: Intended Audience :: Information Technology
Classifier: Intended Audience :: Science/Research
Classifier: Topic :: Software Development :: Build Tools
Classifier: License :: OSI Approved :: BSD License
Classifier: Operating System :: MacOS :: MacOS X
Classifier: Operating System :: Microsoft :: Windows
Classifier: Operating System :: POSIX
Classifier: Natural Language :: English
Classifier: Programming Language :: Python :: 3.6
Classifier: Programming Language :: Python :: 3.7
Classifier: Programming Language :: Python :: 3.8
Classifier: Programming Language :: Python :: 3.9
Classifier: Programming Language :: Python :: 3.10
Classifier: Programming Language :: Python :: 3.11
Classifier: Programming Language :: Python :: Implementation :: CPython
Classifier: Topic :: Database
Classifier: Topic :: Scientific/Engineering
Classifier: Topic :: Software Development
License-File: LICENSE.txt
Requires-Dist: pandas
Requires-Dist: numpy
Requires-Dist: six
Requires-Dist: pypyodbc
Requires-Dist: pyodbc
Requires-Dist: lazy
Requires-Dist: nzpy
Provides-Extra: doc
Requires-Dist: sphinx ; extra == 'doc'
Requires-Dist: ipython ; extra == 'doc'
Requires-Dist: numpydoc ; extra == 'doc'
Requires-Dist: sphinx-rtd-theme ; extra == 'doc'
Provides-Extra: jdbc
Requires-Dist: JayDeBeApi ==1.* ; extra == 'jdbc'
Requires-Dist: Jpype1 ==0.6.3 ; extra == 'jdbc'
Provides-Extra: test
Requires-Dist: pytest ; extra == 'test'
Requires-Dist: flaky ==3.4.0 ; extra == 'test'
